setup.py
test.wiki
KoMar.egg-info/PKG-INFO
KoMar.egg-info/SOURCES.txt
KoMar.egg-info/dependency_links.txt
KoMar.egg-info/entry_points.txt
KoMar.egg-info/top_level.txt
bin/komar
komar/__init__.py