Metadata-Version: 1.0
Name: KoMar
Version: 0.5
Summary: KoMar is simple wiki-markup heavily based on Creole
Home-page: http://www.kosciak.net/KoMar/try
Author: Wojciech 'KosciaK' Pietrzok
Author-email: kosciak@kosciak.net
License: Apache License v2
Keywords: wiki markup parser
Platform: UNKNOWN
Classifier: Development Status :: 4 - Beta
Classifier: Programming Language :: Python
Classifier: Operating System :: POSIX :: Linux
Classifier: Environment :: Console
Classifier: Topic :: Text Processing :: Markup
Classifier: Topic :: Text Processing :: Markup :: HTML
Classifier: License :: OSI Approved :: Apache Software License
